scraper/__init__.py
scraper/cli.py
scraper/scraper.py
scraper/models/__init__.py
scraper/models/builder.py
scraper/models/document.py
scraper/models/element.py
scraper/models/enums.py
scraper/models/exam_info.py
scraper/models/mark_and_points.py
scraper/models/module.py
scraper/models/study_program.py
scraper/models/sub_element.py
wbh_campus_scraper-0.5.2.dist-info/licenses/LICENSE
wbh_campus_scraper-0.5.2.dist-info/METADATA
wbh_campus_scraper-0.5.2.dist-info/WHEEL
wbh_campus_scraper-0.5.2.dist-info/entry_points.txt
wbh_campus_scraper-0.5.2.dist-info/top_level.txt
wbh_campus_scraper-0.5.2.dist-info/RECORD
