Metadata-Version: 2.4
Name: wbh-campus-scraper
Version: 0.5.2
Summary: Extract and process study data from WBH Online Campus HTML exports
Home-page: https://jonaskern.dev
Author: Jonas Kern
Author-email: Jonas Kern <info@jonaskern.de>
License: MIT
Project-URL: Homepage, https://jonaskern.dev
Project-URL: Source, https://github.com/jonaskern-dev/wbh-campus-scraper
Classifier: Development Status :: 4 - Beta
Classifier: Intended Audience :: Education
Classifier: Topic :: Education
Classifier: Programming Language :: Python :: 3
Classifier: Programming Language :: Python :: 3.8
Classifier: Programming Language :: Python :: 3.9
Classifier: Programming Language :: Python :: 3.10
Classifier: Programming Language :: Python :: 3.11
Classifier: Programming Language :: Python :: 3.12
Classifier: Programming Language :: Python :: 3.13
Classifier: License :: OSI Approved :: MIT License
Classifier: Operating System :: OS Independent
Requires-Python: >=3.8
License-File: LICENSE
Dynamic: author
Dynamic: home-page
Dynamic: license-file
Dynamic: requires-python
